{
  "title_a": "死ぬ前に後悔するのは、言わなかった言葉だけだ",
  "title_b": "「あの人に連絡しておけばよかった」——それが最後の後悔になる前に",
  "body": "ある調査で、末期患者が口にする後悔の第一位は「もっと好きな人と時間を過ごせばよかった」だった。仕事の失敗でも、挑戦しなかったことでもない。連絡しなかった、ということだ。\n\n死を前にして人間が初めて見えるものがある。それは「誰が本当に大切だったか」ではなく、「自分は大切な人に、それを伝えたか」という問いだ。\n\n---\n\n## 「後で連絡しよう」は存在しない\n\n今夜、LINEの未読を開いたとき、返していないメッセージがあるとしたら。それが半年以上前のものなら、その相手のことを一度も思い出さなかった半年間が、そこにある。\n\n人は「いつでも連絡できる」という前提で生きている。だから後回しにする。だから「落ち着いたら」「気が向いたら」「年末に」と言いながら、そのまま数年が経つ。\n\nでも「後で」は構造的に存在しない。\n\n今この瞬間だけが、唯一連絡できる場所だ。「後の自分」に委ねた瞬間に、それはほぼ消える。FXをやっていたころ、損切りを「もう少し待ってから」と先延ばしにした瞬間に、ほぼ必ず傷が深くなった。「後で」が機能する場面は、思っているより圧倒的に少ない。\n\n---\n\n## 関係は「続いているもの」ではなく「続けているもの」だ\n\nあなたが今、大切だと思っている人を3人思い浮かべてほしい。\n\nその人たちとの関係は、なぜ今も続いているのか。\n\nたいてい答えは「何かをきっかけに、どちらかが連絡した」からだ。関係は自然に続くものではない。誰かが動いたから続いている。そしてその「誰か」が、ある時期からずっとあなただった関係もあれば、相手だった関係もある。\n\n関係の本質は、感情の総量ではなく、行動の積み重ねだ。「好きだと思っている」だけでは、関係は存在しない。連絡した、会った、何かを言った——その事実の連続だけが関係を構成する。\n\nもちろん、これが全員に当てはまるわけじゃない。距離を置くことで保たれる関係もある。でも——「置いている」と「放置している」は、全く別のことだ。\n\n---\n\n## 「大切にしている」と「大切にしてきた」は違う\n\n人は死に際して、過去形で関係を評価する。\n\n「あの人のことは大切にしていた」と言いたくても、連絡した記録が3年前で止まっているなら、それは「大切にしていた」ではなく「大切だと思っていた」だ。思っていることと、していることは別の次元にある。\n\n自己肯定感の話をよくする文脈で、「自分を大切にすること」が語られる。でも、自分を大切にできる人間は、他者への行動でそれを証明している。大切にするとは、思うことではなく、動くことだ。\n\n1本のLINEで足りる。「元気にしてる？」の6文字で足りる。それすら送れていないとしたら、問題は忙しさではなく、優先順位だ。1日に何回かスマホを開いているなら、時間はある。あるのに動いていない、というのが正確な状態だ。\n\n---\n\n## 今夜、1人に連絡する\n\n大きな行動はいらない。\n\n今、頭に浮かんだ人に、今夜連絡する。それだけでいい。久しぶりすぎて何を言えばいいかわからないなら「久しぶり」と送ればいい。それが全てだ。\n\nなぜこれで足りるのか。関係とは、大きな出来事の集積ではなく、小さな接触の連続だからだ。1回の「久しぶり」は、3年間の沈黙を帳消しにするほどの力を持つ。人間の記憶は、最後に何が起きたかを異常なほど重視する。これは心理学の終末効果として実証されている。最後の印象が、関係全体の評価を塗り替える。\n\nだから今夜連絡することには、「取り戻す」以上の意味がある。今夜の1通が、その人の記憶の中の「あなた」を更新する。\n\n---\n\n全と1は同じ構造をしている。「すべての大切な関係を守ること」と「今夜1人に連絡すること」は、等価だ。後者を実行した人間だけが、前者を手に入れる。\n\n死ぬ前に後悔するのは、大きなことじゃない。送らなかった、あの1通だ。\n\n---\nこのマガジンでは、全ジャンルに通底する「再現の法則」を毎日翻訳しています。\n→ https://note.com/militech_2077/m/mf82e085b93c9",
  "hashtags": [
    "人間関係",
    "死生観",
    "大切な人",
    "自己肯定感",
    "生き方"
  ],
  "topic": {
    "title": "「大切な人に連絡しとけ」——死を前にして初めて気づく、本当に大切な関係とは",
    "keywords": [
      "人間関係",
      "死生観",
      "大切な人"
    ],
    "reason": "危機的状況での人間関係の本質を問う哲学的・感情的テーマとして共感を呼びやすい"
  },
  "created_at": "2026-05-15T09:38:31.007122+00:00"
}